aio_tcpserver/__init__.py
aio_tcpserver/config.py
aio_tcpserver/errors.py
aio_tcpserver/hook.py
aio_tcpserver/log.py
aio_tcpserver/serve_multiple.py
aio_tcpserver/server_single.py
aio_tcpserver/utils.py
aio_tcpserver-0.0.3.data/data/requirements/requirements.txt
aio_tcpserver-0.0.3.data/data/requirements/requirements_dev.txt
aio_tcpserver-0.0.3.data/data/requirements/requirements_test.txt
aio_tcpserver-0.0.3.dist-info/DESCRIPTION.rst
aio_tcpserver-0.0.3.dist-info/METADATA
aio_tcpserver-0.0.3.dist-info/RECORD
aio_tcpserver-0.0.3.dist-info/WHEEL
aio_tcpserver-0.0.3.dist-info/metadata.json
aio_tcpserver-0.0.3.dist-info/top_level.txt
