Metadata-Version: 1.1
Name: aio-tcpserver
Version: 0.0.3
Summary: simple tools
Home-page: https://github.com/Basic-Components/aio-tcpserver
Author: hsz
Author-email: hsz1273327@gmail.com
License: MIT
Keywords: tcp-server,asyncio
Platform: UNKNOWN
Classifier: Development Status :: 3 - Alpha
Classifier: Intended Audience :: Developers
Classifier: License :: OSI Approved :: MIT License
Classifier: Programming Language :: Python :: 3.5
Classifier: Programming Language :: Python :: 3.6
Classifier: Topic :: Documentation :: Sphinx
